{
  "resource_state": 3,
  "athlete": {
    "id": 2170160,
    "resource_state": 1
  },
  "name": "Evening Trail Run",
  "distance": 8318.2,
  "moving_time": 3640,
  "elapsed_time": 3813,
  "total_elevation_gain": 134,
  "type": "Run",
  "sport_type": "TrailRun",
  "workout_type": null,
  "id": 8540192975,
  "start_date": "2023-02-11T01:37:15Z",
  "start_date_local": "2023-02-10T18:37:15Z",
  "timezone": "(GMT-07:00) America/Denver",
  "utc_offset": -25200,
  "location_city": null,
  "location_state": null,
  "location_country": "United States",
  "achievement_count": 0,
  "kudos_count": 3,
  "comment_count": 0,
  "athlete_count": 1,
  "photo_count": 0,
  "map": {
    "id": "a8540192975",
    "polyline": "kodcFfmjqSROEQ?OJMHGTCJJt@Bn@?TETS@CESa@gAAs@[g@SKSYu@m@]_@OKOAM@URe@HiAe@QDUVAH[\\w@bAyBnBuCvAQRAL@`@j@t@Fl@Cr@Gb@Qh@m@~@sAnAMVE`@Kl@s@zAUJSBg@N]?eAq@gBg@o@GUQ{Bq@gBo@wAa@a@Ee@FqA^c@Hq@Cg@QgBcAqBeAg@SSESA]Bg@JqA^yB^eAQWKe@IeAWmAc@u@Ie@@m@FaBZm@Ca@Sa@]MQi@s@mAmBcBiD_@a@cA_AeAuASi@YkBSw@YQmAQG?`@DLAN@j@N\\|@b@rBVr@RVHDp@|@z@x@\\`@^n@^~@j@fAxAxB\\b@PL\\TNBd@@bASvAQbADf@J~Bv@n@L@Dt@HV?nBc@XI@EEYm@aAg@eAk@yAYg@g@m@MYm@[_@a@o@cAQo@Iu@KgEAgABSPYz@gA\\q@Z[f@LNNXPZ?d@Oj@Kd@FHH^ZJJQE_@QWGS?U@{@T]A_@]c@MWPSl@e@n@g@^WGs@}Ae@yAQ_AIs@C{@Im@Mc@Se@m@eAc@m@k@s@c@Yi@Oo@DMH{@PY?c@[[]g@o@SOSEs@HW?IDnA[ZB\\Td@n@b@d@PFZApA]d@EL@TFt@h@d@p@xAbCVr@Lz@JtALdAHZfA`DFv@AbA@PBtAHxAP`BN\\bApAfA`ANXh@t@HNGG@GBBBCA@AC`BvD^l@PPZ@|@Mb@D^Jd@RjB`A`@PTDAB@Cr@d@b@JZ@b@En@OvAO`@BrA^h@TnAVlDdAVDbAVj@Vh@\\V@fA_@JI^q@f@gCX[\\SJKx@aAR_@Lm@@a@C_@Mo@Qa@Ye@@a@DIV[bA_@d@UnA_A^_@|@o@\\a@XUv@w@TAPB`@RX@`AYf@V~@|@TNx@b@RTDHDXChAVv@ADKN[Rc@?a@Es@B[NGJ?D",
    "resource_state": 3,
    "summary_polyline": "kodcFfmjqSROEQ?OJMHGTCJJt@Bn@?TETS@CESa@gAAs@[g@SKSYu@m@]_@OKOAM@URe@HiAe@QDUVAH[\\w@bAyBnBuCvAQRAL@`@j@t@Fl@Cr@Gb@Qh@m@~@sAnAMVE`@Kl@s@zAUJSBg@N]?eAq@gBg@o@GUQ{Bq@gBo@wAa@a@Ee@FqA^c@Hq@Cg@QgBcAqBeAg@SSESA]Bg@JqA^yB^eAQWKe@IeAWmAc@u@Ie@@m@FaBZm@Ca@Sa@]MQi@s@mAmBcBiD_@a@cA_AeAuASi@YkBSw@YQmAQG?`@DLAN@j@N\\|@b@rBVr@RVHDp@|@z@x@\\`@^n@^~@j@fAxAxB\\b@PL\\TNBd@@bASvAQbADf@J~Bv@n@L@Dt@HV?nBc@XI@EEYm@aAg@eAk@yAYg@g@m@MYm@[_@a@o@cAQo@Iu@KgEAgABSPYz@gA\\q@Z[f@LNNXPZ?d@Oj@Kd@FHH^ZJJQE_@QWGS?U@{@T]A_@]c@MWPSl@e@n@g@^WGs@}Ae@yAQ_AIs@C{@Im@Mc@Se@m@eAc@m@k@s@c@Yi@Oo@DMH{@PY?c@[[]g@o@SOSEs@HW?IDnA[ZB\\Td@n@b@d@PFZApA]d@EL@TFt@h@d@p@xAbCVr@Lz@JtALdAHZfA`DFv@AbA@PBtAHxAP`BN\\bApAfA`ANXh@t@HNGG@GBBBCA@AC`BvD^l@PPZ@|@Mb@D^Jd@RjB`A`@PTDAB@Cr@d@b@JZ@b@En@OvAO`@BrA^h@TnAVlDdAVDbAVj@Vh@\\V@fA_@JI^q@f@gCX[\\SJKx@aAR_@Lm@@a@C_@Mo@Qa@Ye@@a@DIV[bA_@d@UnA_A^_@|@o@\\a@XUv@w@TAPB`@RX@`AYf@V~@|@TNx@b@RTDHDXChAVv@ADKN[Rc@?a@Es@B[NGJ?D"
  },
  "trainer": false,
  "commute": false,
  "manual": false,
  "private": false,
  "visibility": "everyone",
  "flagged": false,
  "gear_id": null,
  "start_latlng": [
    37.38374378532171,
    -107.86531263962388
  ],
  "end_latlng": [
    37.383603136986494,
    -107.86520585417747
  ],
  "average_speed": 2.285,
  "max_speed": 3.841,
  "average_cadence": 77.9,
  "average_temp": 21,
  "has_heartrate": true,
  "average_heartrate": 119.1,
  "max_heartrate": 155,
  "heartrate_opt_out": false,
  "display_hide_heartrate_option": true,
  "elev_high": 2310.8,
  "elev_low": 2236.2,
  "upload_id": 9167077485,
  "upload_id_str": "9167077485",
  "external_id": "garmin_ping_259510322352",
  "from_accepted_tag": false,
  "pr_count": 0,
  "total_photo_count": 0,
  "has_kudoed": false,
  "suffer_score": 21,
  "description": null,
  "calories": 524,
  "perceived_exertion": null,
  "prefer_perceived_exertion": null,
  "segment_efforts": [
    {
      "id": 3059319216667332600,
      "resource_state": 2,
      "name": "North Main Climb",
      "activity": {
        "id": 8540192975,
        "visibility": "everyone",
        "resource_state": 1
      },
      "athlete": {
        "id": 2170160,
        "resource_state": 1
      },
      "elapsed_time": 227,
      "moving_time": 227,
      "start_date": "2023-02-11T01:50:37Z",
      "start_date_local": "2023-02-10T18:50:37Z",
      "distance": 553.4,
      "start_index": 197,
      "end_index": 250,
      "average_cadence": 80.9,
      "device_watts": false,
      "average_heartrate": 134,
      "max_heartrate": 153,
      "segment": {
        "id": 33615103,
        "resource_state": 2,
        "name": "North Main Climb",
        "activity_type": "Run",
        "distance": 553.4,
        "average_grade": 3.9,
        "maximum_grade": 7.9,
        "elevation_high": 2314.4,
        "elevation_low": 2292.8,
        "start_latlng": [
          37.394662,
          -107.866605
        ],
        "end_latlng": [
          37.399121,
          -107.865038
        ],
        "elevation_profile": null,
        "climb_category": 0,
        "city": null,
        "state": "Colorado",
        "country": "USA",
        "private": false,
        "hazardous": true,
        "starred": true
      },
      "pr_rank": null,
      "achievements": [],
      "visibility": "everyone",
      "kom_rank": null,
      "hidden": false
    },
    {
      "id": 3078740095725103600,
      "resource_state": 2,
      "name": "Oakcrest climb",
      "activity": {
        "id": 8540192975,
        "visibility": "everyone",
        "resource_state": 1
      },
      "athlete": {
        "id": 2170160,
        "resource_state": 1
      },
      "elapsed_time": 120,
      "moving_time": 120,
      "start_date": "2023-02-11T02:10:19Z",
      "start_date_local": "2023-02-10T19:10:19Z",
      "distance": 270.4,
      "start_index": 483,
      "end_index": 520,
      "average_cadence": 80.6,
      "device_watts": false,
      "average_heartrate": 137.3,
      "max_heartrate": 149,
      "segment": {
        "id": 34080682,
        "resource_state": 2,
        "name": "Oakcrest climb",
        "activity_type": "Run",
        "distance": 270.4,
        "average_grade": 8.8,
        "maximum_grade": 15,
        "elevation_high": 2311.8,
        "elevation_low": 2288,
        "start_latlng": [
          37.397021,
          -107.859866
        ],
        "end_latlng": [
          37.398928,
          -107.858619
        ],
        "elevation_profile": null,
        "climb_category": 0,
        "city": null,
        "state": "Colorado",
        "country": "USA",
        "private": false,
        "hazardous": false,
        "starred": false
      },
      "pr_rank": null,
      "achievements": [
        {
          "type_id": 7,
          "type": "segment_effort_count_leader",
          "rank": 1,
          "effort_count": 1
        }
      ],
      "visibility": "everyone",
      "kom_rank": null,
      "hidden": false
    },
    {
      "id": 3059319216664087600,
      "resource_state": 2,
      "name": "Oakcrest to Home",
      "activity": {
        "id": 8540192975,
        "visibility": "everyone",
        "resource_state": 1
      },
      "athlete": {
        "id": 2170160,
        "resource_state": 1
      },
      "elapsed_time": 681,
      "moving_time": 663,
      "start_date": "2023-02-11T02:28:33Z",
      "start_date_local": "2023-02-10T19:28:33Z",
      "distance": 1681.6,
      "start_index": 700,
      "end_index": 855,
      "average_cadence": 77.1,
      "device_watts": false,
      "average_heartrate": 106.4,
      "max_heartrate": 117,
      "segment": {
        "id": 31263808,
        "resource_state": 2,
        "name": "Oakcrest to Home",
        "activity_type": "Run",
        "distance": 1681.6,
        "average_grade": -2.5,
        "maximum_grade": 1.8,
        "elevation_high": 2291.2,
        "elevation_low": 2249.4,
        "start_latlng": [
          37.394097,
          -107.866296
        ],
        "end_latlng": [
          37.382619,
          -107.864783
        ],
        "elevation_profile": null,
        "climb_category": 0,
        "city": "Durango",
        "state": "Colorado",
        "country": "United States",
        "private": true,
        "hazardous": false,
        "starred": false
      },
      "pr_rank": null,
      "achievements": [],
      "visibility": "everyone",
      "kom_rank": null,
      "hidden": false
    },
    {
      "id": 3059319216664619000,
      "resource_state": 2,
      "name": "Down Snowshoe",
      "activity": {
        "id": 8540192975,
        "visibility": "everyone",
        "resource_state": 1
      },
      "athlete": {
        "id": 2170160,
        "resource_state": 1
      },
      "elapsed_time": 365,
      "moving_time": 365,
      "start_date": "2023-02-11T02:33:43Z",
      "start_date_local": "2023-02-10T19:33:43Z",
      "distance": 928.4,
      "start_index": 769,
      "end_index": 854,
      "average_cadence": 78.8,
      "device_watts": false,
      "average_heartrate": 107,
      "max_heartrate": 117,
      "segment": {
        "id": 31263972,
        "resource_state": 2,
        "name": "Down Snowshoe",
        "activity_type": "Run",
        "distance": 928.4,
        "average_grade": -2.7,
        "maximum_grade": 2.6,
        "elevation_high": 2276.6,
        "elevation_low": 2251.6,
        "start_latlng": [
          37.387703,
          -107.86803
        ],
        "end_latlng": [
          37.382633,
          -107.864748
        ],
        "elevation_profile": null,
        "climb_category": 0,
        "city": "Durango",
        "state": "Colorado",
        "country": "United States",
        "private": true,
        "hazardous": false,
        "starred": false
      },
      "pr_rank": null,
      "achievements": [],
      "visibility": "everyone",
      "kom_rank": null,
      "hidden": false
    }
  ],
  "splits_metric": [
    {
      "distance": 1000.5,
      "elapsed_time": 435,
      "elevation_difference": 16.6,
      "moving_time": 435,
      "split": 1,
      "average_speed": 2.3,
      "average_grade_adjusted_speed": 2.48,
      "average_heartrate": 138.5523114355231,
      "pace_zone": 1
    },
    {
      "distance": 1006.3,
      "elapsed_time": 418,
      "elevation_difference": 37.8,
      "moving_time": 407,
      "split": 2,
      "average_speed": 2.47,
      "average_grade_adjusted_speed": 2.82,
      "average_heartrate": 148.3955773955774,
      "pace_zone": 1
    },
    {
      "distance": 994.5,
      "elapsed_time": 385,
      "elevation_difference": 6,
      "moving_time": 385,
      "split": 3,
      "average_speed": 2.58,
      "average_grade_adjusted_speed": 2.73,
      "average_heartrate": 124.48311688311688,
      "pace_zone": 1
    },
    {
      "distance": 1007.8,
      "elapsed_time": 400,
      "elevation_difference": -14.8,
      "moving_time": 344,
      "split": 4,
      "average_speed": 2.93,
      "average_grade_adjusted_speed": 2.92,
      "average_heartrate": 120.88011695906432,
      "pace_zone": 1
    },
    {
      "distance": 991.8,
      "elapsed_time": 361,
      "elevation_difference": -3.2,
      "moving_time": 361,
      "split": 5,
      "average_speed": 2.75,
      "average_grade_adjusted_speed": 2.78,
      "average_heartrate": 118.58725761772853,
      "pace_zone": 1
    },
    {
      "distance": 1004.8,
      "elapsed_time": 514,
      "elevation_difference": -2.2,
      "moving_time": 407,
      "split": 6,
      "average_speed": 2.47,
      "average_grade_adjusted_speed": 2.69,
      "average_heartrate": 117.92364532019704,
      "pace_zone": 1
    },
    {
      "distance": 1011.7,
      "elapsed_time": 777,
      "elevation_difference": -9.6,
      "moving_time": 777,
      "split": 7,
      "average_speed": 1.3,
      "average_grade_adjusted_speed": 1.29,
      "average_heartrate": 90.05350553505535,
      "pace_zone": 1
    },
    {
      "distance": 986.1,
      "elapsed_time": 394,
      "elevation_difference": -19.8,
      "moving_time": 394,
      "split": 8,
      "average_speed": 2.5,
      "average_grade_adjusted_speed": 2.42,
      "average_heartrate": 108.39340101522842,
      "pace_zone": 1
    },
    {
      "distance": 315.6,
      "elapsed_time": 129,
      "elevation_difference": -10.6,
      "moving_time": 129,
      "split": 9,
      "average_speed": 2.45,
      "average_grade_adjusted_speed": 2.33,
      "average_heartrate": 103.11627906976744,
      "pace_zone": 1
    }
  ],
  "splits_standard": [
    {
      "distance": 1611.3,
      "elapsed_time": 686,
      "elevation_difference": 31.6,
      "moving_time": 675,
      "split": 1,
      "average_speed": 2.39,
      "average_grade_adjusted_speed": 2.59,
      "average_heartrate": 142.110599078341,
      "pace_zone": 1
    },
    {
      "distance": 1609.1,
      "elapsed_time": 639,
      "elevation_difference": 37,
      "moving_time": 639,
      "split": 2,
      "average_speed": 2.52,
      "average_grade_adjusted_speed": 2.81,
      "average_heartrate": 132.18779342723005,
      "pace_zone": 1
    },
    {
      "distance": 1608.4,
      "elapsed_time": 610,
      "elevation_difference": -30.2,
      "moving_time": 554,
      "split": 3,
      "average_speed": 2.9,
      "average_grade_adjusted_speed": 2.83,
      "average_heartrate": 117.15760869565217,
      "pace_zone": 1
    },
    {
      "distance": 1610.1,
      "elapsed_time": 1117,
      "elevation_difference": 7.4,
      "moving_time": 1010,
      "split": 4,
      "average_speed": 1.59,
      "average_grade_adjusted_speed": 1.71,
      "average_heartrate": 102.6199494949495,
      "pace_zone": 1
    },
    {
      "distance": 1609.1,
      "elapsed_time": 649,
      "elevation_difference": -38.4,
      "moving_time": 649,
      "split": 5,
      "average_speed": 2.48,
      "average_grade_adjusted_speed": 2.38,
      "average_heartrate": 107.22028526148969,
      "pace_zone": 1
    },
    {
      "distance": 271.1,
      "elapsed_time": 112,
      "elevation_difference": -7.2,
      "moving_time": 112,
      "split": 6,
      "average_speed": 2.42,
      "average_grade_adjusted_speed": 2.34,
      "average_heartrate": 102.94642857142857,
      "pace_zone": 1
    }
  ],
  "laps": [
    {
      "id": 28821230578,
      "resource_state": 2,
      "name": "Lap 1",
      "activity": {
        "id": 8540192975,
        "visibility": "everyone",
        "resource_state": 1
      },
      "athlete": {
        "id": 2170160,
        "resource_state": 1
      },
      "elapsed_time": 686,
      "moving_time": 675,
      "start_date": "2023-02-11T01:37:15Z",
      "start_date_local": "2023-02-10T18:37:15Z",
      "distance": 1609.34,
      "average_speed": 2.38,
      "max_speed": 3.31,
      "lap_index": 1,
      "split": 1,
      "start_index": 0,
      "end_index": 167,
      "total_elevation_gain": 38.4,
      "average_cadence": 81.6,
      "device_watts": false,
      "average_heartrate": 142.1,
      "max_heartrate": 155,
      "pace_zone": 1
    },
    {
      "id": 28821230579,
      "resource_state": 2,
      "name": "Lap 2",
      "activity": {
        "id": 8540192975,
        "visibility": "everyone",
        "resource_state": 1
      },
      "athlete": {
        "id": 2170160,
        "resource_state": 1
      },
      "elapsed_time": 639,
      "moving_time": 639,
      "start_date": "2023-02-11T01:48:42Z",
      "start_date_local": "2023-02-10T18:48:42Z",
      "distance": 1609.34,
      "average_speed": 2.52,
      "max_speed": 3.608,
      "lap_index": 2,
      "split": 2,
      "start_index": 168,
      "end_index": 334,
      "total_elevation_gain": 57.4,
      "average_cadence": 81,
      "device_watts": false,
      "average_heartrate": 132.2,
      "max_heartrate": 155,
      "pace_zone": 1
    },
    {
      "id": 28821230580,
      "resource_state": 2,
      "name": "Lap 3",
      "activity": {
        "id": 8540192975,
        "visibility": "everyone",
        "resource_state": 1
      },
      "athlete": {
        "id": 2170160,
        "resource_state": 1
      },
      "elapsed_time": 610,
      "moving_time": 554,
      "start_date": "2023-02-11T01:59:24Z",
      "start_date_local": "2023-02-10T18:59:24Z",
      "distance": 1609.34,
      "average_speed": 2.9,
      "max_speed": 3.841,
      "lap_index": 3,
      "split": 3,
      "start_index": 335,
      "end_index": 474,
      "total_elevation_gain": 10.6,
      "average_cadence": 82.1,
      "device_watts": false,
      "average_heartrate": 117.1,
      "max_heartrate": 130,
      "pace_zone": 1
    },
    {
      "id": 28821230581,
      "resource_state": 2,
      "name": "Lap 4",
      "activity": {
        "id": 8540192975,
        "visibility": "everyone",
        "resource_state": 1
      },
      "athlete": {
        "id": 2170160,
        "resource_state": 1
      },
      "elapsed_time": 1116,
      "moving_time": 1010,
      "start_date": "2023-02-11T02:09:34Z",
      "start_date_local": "2023-02-10T19:09:34Z",
      "distance": 1609.34,
      "average_speed": 1.59,
      "max_speed": 3.494,
      "lap_index": 4,
      "split": 4,
      "start_index": 475,
      "end_index": 692,
      "total_elevation_gain": 36.2,
      "average_cadence": 68.2,
      "device_watts": false,
      "average_heartrate": 102.6,
      "max_heartrate": 149,
      "pace_zone": 1
    },
    {
      "id": 28821230582,
      "resource_state": 2,
      "name": "Lap 5",
      "activity": {
        "id": 8540192975,
        "visibility": "everyone",
        "resource_state": 1
      },
      "athlete": {
        "id": 2170160,
        "resource_state": 1
      },
      "elapsed_time": 649,
      "moving_time": 649,
      "start_date": "2023-02-11T02:28:11Z",
      "start_date_local": "2023-02-10T19:28:11Z",
      "distance": 1609.34,
      "average_speed": 2.48,
      "max_speed": 2.949,
      "lap_index": 5,
      "split": 5,
      "start_index": 693,
      "end_index": 839,
      "total_elevation_gain": 2.6,
      "average_cadence": 78.8,
      "device_watts": false,
      "average_heartrate": 107.3,
      "max_heartrate": 117,
      "pace_zone": 1
    },
    {
      "id": 28821230583,
      "resource_state": 2,
      "name": "Lap 6",
      "activity": {
        "id": 8540192975,
        "visibility": "everyone",
        "resource_state": 1
      },
      "athlete": {
        "id": 2170160,
        "resource_state": 1
      },
      "elapsed_time": 112,
      "moving_time": 112,
      "start_date": "2023-02-11T02:39:00Z",
      "start_date_local": "2023-02-10T19:39:00Z",
      "distance": 272.39,
      "average_speed": 2.43,
      "max_speed": 3.086,
      "lap_index": 6,
      "split": 6,
      "start_index": 840,
      "end_index": 868,
      "total_elevation_gain": 0,
      "average_cadence": 78.3,
      "device_watts": false,
      "average_heartrate": 102.9,
      "max_heartrate": 112,
      "pace_zone": 1
    }
  ],
  "best_efforts": [
    {
      "id": 24190268715,
      "resource_state": 2,
      "name": "400m",
      "activity": {
        "id": 8540192975,
        "visibility": "everyone",
        "resource_state": 1
      },
      "athlete": {
        "id": 2170160,
        "resource_state": 1
      },
      "elapsed_time": 138,
      "moving_time": 138,
      "start_date": "2023-02-11T01:59:10Z",
      "start_date_local": "2023-02-10T18:59:10Z",
      "distance": 400,
      "pr_rank": null,
      "achievements": [],
      "start_index": 331,
      "end_index": 367
    },
    {
      "id": 24190268719,
      "resource_state": 2,
      "name": "1/2 mile",
      "activity": {
        "id": 8540192975,
        "visibility": "everyone",
        "resource_state": 1
      },
      "athlete": {
        "id": 2170160,
        "resource_state": 1
      },
      "elapsed_time": 291,
      "moving_time": 291,
      "start_date": "2023-02-11T01:58:49Z",
      "start_date_local": "2023-02-10T18:58:49Z",
      "distance": 805,
      "pr_rank": null,
      "achievements": [],
      "start_index": 327,
      "end_index": 399
    },
    {
      "id": 24190268722,
      "resource_state": 2,
      "name": "1k",
      "activity": {
        "id": 8540192975,
        "visibility": "everyone",
        "resource_state": 1
      },
      "athlete": {
        "id": 2170160,
        "resource_state": 1
      },
      "elapsed_time": 363,
      "moving_time": 363,
      "start_date": "2023-02-11T02:04:08Z",
      "start_date_local": "2023-02-10T19:04:08Z",
      "distance": 1000,
      "pr_rank": null,
      "achievements": [],
      "start_index": 402,
      "end_index": 482
    },
    {
      "id": 24190268728,
      "resource_state": 2,
      "name": "1 mile",
      "activity": {
        "id": 8540192975,
        "visibility": "everyone",
        "resource_state": 1
      },
      "athlete": {
        "id": 2170160,
        "resource_state": 1
      },
      "elapsed_time": 604,
      "moving_time": 604,
      "start_date": "2023-02-11T01:53:33Z",
      "start_date_local": "2023-02-10T18:53:33Z",
      "distance": 1609,
      "pr_rank": null,
      "achievements": [],
      "start_index": 239,
      "end_index": 398
    },
    {
      "id": 24190268735,
      "resource_state": 2,
      "name": "2 mile",
      "activity": {
        "id": 8540192975,
        "visibility": "everyone",
        "resource_state": 1
      },
      "athlete": {
        "id": 2170160,
        "resource_state": 1
      },
      "elapsed_time": 1239,
      "moving_time": 1239,
      "start_date": "2023-02-11T01:52:15Z",
      "start_date_local": "2023-02-10T18:52:15Z",
      "distance": 3219,
      "pr_rank": null,
      "achievements": [],
      "start_index": 221,
      "end_index": 528
    },
    {
      "id": 24190268739,
      "resource_state": 2,
      "name": "5k",
      "activity": {
        "id": 8540192975,
        "visibility": "everyone",
        "resource_state": 1
      },
      "athlete": {
        "id": 2170160,
        "resource_state": 1
      },
      "elapsed_time": 1970,
      "moving_time": 1970,
      "start_date": "2023-02-11T01:40:16Z",
      "start_date_local": "2023-02-10T18:40:16Z",
      "distance": 5000,
      "pr_rank": null,
      "achievements": [],
      "start_index": 61,
      "end_index": 531
    }
  ],
  "photos": {
    "primary": null,
    "count": 0
  },
  "stats_visibility": [
    {
      "type": "heart_rate",
      "visibility": "everyone"
    },
    {
      "type": "pace",
      "visibility": "everyone"
    },
    {
      "type": "power",
      "visibility": "everyone"
    },
    {
      "type": "speed",
      "visibility": "everyone"
    },
    {
      "type": "calories",
      "visibility": "everyone"
    }
  ],
  "hide_from_home": false,
  "device_name": "Garmin Enduro",
  "embed_token": "a363a3ed2c953397ab6342fe2d2ea484c97c6c8b",
  "similar_activities": {
    "effort_count": 14,
    "average_speed": 2.695457648623407,
    "min_average_speed": 2.1487298780871975,
    "mid_average_speed": 2.593493293460978,
    "max_average_speed": 3.270437916603305,
    "pr_rank": null,
    "frequency_milestone": null,
    "trend": {
      "speeds": [
        2.9432875507415304,
        2.773073779458779,
        2.580655980211312,
        2.485516745486323,
        2.4075570034517355
      ],
      "current_activity_index": 2,
      "min_speed": 2.1487298780871975,
      "mid_speed": 2.593493293460978,
      "max_speed": 3.270437916603305,
      "direction": 0
    },
    "resource_state": 2
  },
  "available_zones": [
    "heartrate",
    "pace"
  ]
}