[
  {
    "firstName": "Trevor",
    "lastName": "Hefley",
    "age": "M30-39",
    "location": "MANHATTAN, KS",
    "rank": 97.2,
    "ageRank": 98.3,
    "results": 2,
    "bib": "",
    "finishes": 1
  },
  {
    "firstName": "Randall",
    "lastName": "Fish",
    "age": "M50-59",
    "location": "Wamego, KS",
    "rank": 74,
    "ageRank": 73.9,
    "results": 6,
    "bib": "",
    "finishes": 0
  },
  {
    "firstName": "Bailey",
    "lastName": "Dantonio",
    "age": "F30-39",
    "location": "Seattle, WA",
    "rank": 84.3,
    "ageRank": 87.5,
    "results": 4,
    "bib": "",
    "finishes": 0
  },
  {
    "firstName": "Muriel",
    "lastName": "Greening",
    "age": "F40-49",
    "location": "Broomfield, CO",
    "rank": 80.7,
    "ageRank": 81.3,
    "results": 22,
    "bib": "",
    "finishes": 0
  },
  {
    "firstName": "Chase",
    "lastName": "Herrick",
    "age": "M20-29",
    "location": "Wheatridge, CO",
    "rank": 65.5,
    "ageRank": 73.7,
    "results": 5,
    "bib": "",
    "finishes": 0
  },
  {
    "firstName": "Amy",
    "lastName": "Fish",
    "age": "F40-49",
    "location": "Wamego, KS",
    "rank": 73,
    "ageRank": 80.1,
    "results": 5,
    "bib": "",
    "finishes": 0
  },
  {
    "firstName": "Phillip",
    "lastName": "Watson",
    "age": "M40-49",
    "location": "Isanti, MN",
    "rank": 54.9,
    "ageRank": 64.3,
    "results": 18,
    "bib": "",
    "finishes": 0
  },
  {
    "firstName": "Barb",
    "lastName": "Knight",
    "age": "F60-69",
    "location": "Fulton, IL",
    "rank": 61.4,
    "ageRank": 75.9,
    "results": 31,
    "bib": "",
    "finishes": 0
  },
  {
    "firstName": "Althea",
    "lastName": "Schnacke",
    "age": "F40-49",
    "location": "Lawrence, KS",
    "rank": 56.3,
    "ageRank": 57.4,
    "results": 2,
    "bib": "",
    "finishes": 0
  },
  {
    "firstName": "Rob",
    "lastName": "Hastings",
    "age": "M30-39",
    "location": "St. Petersburg, FL",
    "rank": 46.2,
    "ageRank": 47.9,
    "results": 3,
    "bib": "",
    "finishes": 0
  },
  {
    "firstName": "Trista",
    "lastName": "Turney",
    "age": "F50-59",
    "location": "Blanchard, OK",
    "rank": 49.3,
    "ageRank": 63.9,
    "results": 15,
    "bib": "",
    "finishes": 0
  },
  {
    "firstName": "Rebekah",
    "lastName": "Watson",
    "age": "F<20",
    "location": "Elk River, MN",
    "rank": 42.8,
    "ageRank": 64.6,
    "results": 1,
    "bib": "",
    "finishes": 0
  },
  {
    "firstName": "Elizabeth",
    "lastName": "McBride",
    "age": "F40-49",
    "location": "Walnut, KS",
    "rank": 0,
    "ageRank": 0,
    "results": 0,
    "bib": "",
    "finishes": 0
  },
  {
    "firstName": "Kim",
    "lastName": "Rymanowski",
    "age": "F50-59",
    "location": "Odessa, FL",
    "rank": 0,
    "ageRank": 0,
    "results": 0,
    "bib": "",
    "finishes": 0
  },
  {
    "firstName": "Kate",
    "lastName": "Satsky",
    "age": "F20-29",
    "location": "Manhattan, KS",
    "rank": 0,
    "ageRank": 0,
    "results": 0,
    "bib": "",
    "finishes": 0
  },
  {
    "firstName": "Caroline",
    "lastName": "Satsky",
    "age": "F20-29",
    "location": "Lake Quivira, KS",
    "rank": 0,
    "ageRank": 0,
    "results": 0,
    "bib": "",
    "finishes": 0
  },
  {
    "firstName": "Aimee",
    "lastName": "Kopp",
    "age": "F50-59",
    "location": "Evergreen, CO",
    "rank": 0,
    "ageRank": 0,
    "results": 0,
    "bib": "",
    "finishes": 0
  },
  {
    "firstName": "Gabriel",
    "lastName": "Wiley",
    "age": "M20-29",
    "location": "Steamboat Springs, CO",
    "rank": 0,
    "ageRank": 0,
    "results": 0,
    "bib": "",
    "finishes": 0
  },
  {
    "firstName": "Kamryn",
    "lastName": "Graeve",
    "age": "F20-29",
    "location": "Omaha, NE",
    "rank": 0,
    "ageRank": 0,
    "results": 0,
    "bib": "",
    "finishes": 0
  },
  {
    "firstName": "Lisa",
    "lastName": "O’Halloran",
    "age": "F60-69",
    "location": "Overland Park, KS",
    "rank": 0,
    "ageRank": 0,
    "results": 0,
    "bib": "",
    "finishes": 0
  },
  {
    "firstName": "Lucas",
    "lastName": "Holdren",
    "age": "M20-29",
    "location": "MANHATTAN, KS",
    "rank": 0,
    "ageRank": 0,
    "results": 0,
    "bib": "",
    "finishes": 0
  }
]